plover_modal_dictionary/__init__.py
plover_modal_dictionary/dictionary.py
plover_modal_dictionary/extension.py
plover_modal_dictionary-0.0.3.dist-info/LICENSE.txt
plover_modal_dictionary-0.0.3.dist-info/METADATA
plover_modal_dictionary-0.0.3.dist-info/WHEEL
plover_modal_dictionary-0.0.3.dist-info/entry_points.txt
plover_modal_dictionary-0.0.3.dist-info/top_level.txt
plover_modal_dictionary-0.0.3.dist-info/zip-safe
plover_modal_dictionary-0.0.3.dist-info/RECORD
